Metadata-Version: 1.0
Name: pypiTestWY-distributions
Version: 1.0
Summary: Gaussian and Binomial distributions
Home-page: UNKNOWN
Author: wyang03
Author-email: myemail@something.com
License: UNKNOWN
Platform: UNKNOWN
